CHANGELOG.md
LICENSE
cloudmage/jinjautils/__init__.py
cloudmage/jinjautils/jinja.py
cloudmage_jinjautils-1.0.7.dist-info/LICENSE
cloudmage_jinjautils-1.0.7.dist-info/METADATA
cloudmage_jinjautils-1.0.7.dist-info/WHEEL
cloudmage_jinjautils-1.0.7.dist-info/entry_points.txt
cloudmage_jinjautils-1.0.7.dist-info/RECORD
