Metadata-Version: 2.1
Name: cloudmage-jinjautils
Version: 1.0.7
Summary: Quickly and easily define, load, render and write Jinja templates.
Home-page: https://github.com/CloudMaege/PYPKG-JinjaUtils
License: GPL-3.0-or-later
Keywords: Packages,CloudMage,CloudMaege,CloudMæge,Jinja
Author: Rich Naeson
Author-email: cloudmaege@naeson.nl
Maintainer: Rich Naeson
Maintainer-email: cloudmaege@naeson.nl
Requires-Python: >=3.10,<4.0
Classifier: Environment :: Console
Classifier: License :: OSI Approved :: GNU General Public License v3 or later (GPLv3+)
Classifier: Operating System :: OS Independent
Classifier: Programming Language :: Python :: 3
Classifier: Programming Language :: Python :: 3.10
Classifier: Programming Language :: Python :: 3.11
Classifier: Topic :: Software Development :: Documentation
Classifier: Topic :: Software Development :: Libraries :: Python Modules
Requires-Dist: jinja2 (>=3.1.2,<4.0.0)
Project-URL: Documentation, https://github.com/CloudMaege/PYPKG-JinjaUtils
Project-URL: Issues, https://github.com/CloudMaege/PYPKG-JinjaUtils/issues
Project-URL: Repository, https://github.com/CloudMaege/PYPKG-JinjaUtils
Project-URL: Releases, https://github.com/CloudMaege/PYPKG-JinjaUtils/releases
